dataframe_processor/__init__.py
dataframe_processor/processor.py
dataframe_processor/table_schema/__init__.py
dataframe_processor/table_schema/schema.py
dataframe_processor/table_schema/validators.py
django_dataframe_processor/__init__.py
django_dataframe_processor/file_processor.py
pandas-file-processor/__init__.py
pandas-file-processor/file_processor.py
django_dataframe_processor-0.1.2.dist-info/LICENSE
django_dataframe_processor-0.1.2.dist-info/METADATA
django_dataframe_processor-0.1.2.dist-info/WHEEL
django_dataframe_processor-0.1.2.dist-info/top_level.txt
django_dataframe_processor-0.1.2.dist-info/RECORD
