Metadata-Version: 2.1
Name: django-dataframe-processor
Version: 0.1.2
Summary: A Django library for validating and process lines from a pandas DataFrame
Home-page: https://github.com/rrbraz/django-dataframe-processor/
Author: Rafael Rodrigues Braz
License: MIT
Platform: UNKNOWN
Requires-Dist: django
Requires-Dist: pandas
